jps_jira_workspace_utils/__init__.py
jps_jira_workspace_utils/create_git_branch_for_jira_issue.py
jps_jira_workspace_utils/create_jira_workspace.py
jps_jira_workspace_utils/help.py
jps_jira_workspace_utils-1.4.0.dist-info/licenses/LICENSE
jps_jira_workspace_utils-1.4.0.dist-info/METADATA
jps_jira_workspace_utils-1.4.0.dist-info/WHEEL
jps_jira_workspace_utils-1.4.0.dist-info/entry_points.txt
jps_jira_workspace_utils-1.4.0.dist-info/top_level.txt
jps_jira_workspace_utils-1.4.0.dist-info/RECORD
