Metadata-Version: 2.4
Name: jps-jira-workspace-utils
Version: 1.4.0
Summary: Utility for creating Jira workspaces, managing Git branches for Jira issues, and seeding standardized README files.
Author-email: Jaideep Sundaram <jai-python3@gmail.com>
Maintainer-email: Jaideep Sundaram <jai-python3@gmail.com>
License-Expression: MIT
Project-URL: Homepage, https://github.com/jai-python3/jps-jira-workspace-utils
Project-URL: Repository, https://github.com/jai-python3/jps-jira-workspace-utils
Project-URL: Issues, https://github.com/jai-python3/jps-jira-workspace-utils/issues
Keywords: jira,workspace,automation,cli,git,branch
Classifier: Programming Language :: Python :: 3
Classifier: Operating System :: OS Independent
Requires-Python: >=3.9
License-File: LICENSE
Requires-Dist: python-dotenv>=1.0.1
Requires-Dist: requests>=2.32.0
Provides-Extra: dev
Requires-Dist: flake8>=7.0.0; extra == "dev"
Requires-Dist: black>=24.0.0; extra == "dev"
Requires-Dist: build>=1.2.1; extra == "dev"
Requires-Dist: twine>=5.0.0; extra == "dev"
Requires-Dist: pytest>=8.0.0; extra == "dev"
Requires-Dist: pytest-cov>=5.0.0; extra == "dev"
Requires-Dist: isort>=5.13.0; extra == "dev"
Requires-Dist: codecov>=2.1.13; extra == "dev"
Requires-Dist: autoflake>=2.3.1; extra == "dev"
Requires-Dist: pre-commit>=3.8.0; extra == "dev"
Requires-Dist: bandit>=1.7.9; extra == "dev"
Requires-Dist: vulture>=2.11; extra == "dev"
Requires-Dist: flynt>=1.0.1; extra == "dev"
Requires-Dist: pydocstyle>=6.3.0; extra == "dev"
Requires-Dist: darglint>=1.8.1; extra == "dev"
Requires-Dist: mypy>=1.12.1; extra == "dev"
Dynamic: license-file
